README.md
logs_parser/analyzer/__init__.py
logs_parser/analyzer/analyzer.py
logs_parser/analyzer/data/IP2LOCATION-LITE-DB11.BIN
logs_parser/analyzer/data/LICENSE_LITE.TXT
logs_parser/analyzer/data/README_LITE.TXT
logs_parser/analyzer/plots.py
logs_parser/parser/__init__.py
logs_parser/parser/filter.py
logs_parser/parser/log_structure.py
logs_parser/parser/logs_reader.py
logs_parser/parser/logs_writer.py
logs_parser/parser/parser.py
logs_parser/python_callables.py
logsparsersubsystem-1.0.6.dist-info/METADATA
logsparsersubsystem-1.0.6.dist-info/WHEEL
logsparsersubsystem-1.0.6.dist-info/RECORD
