Metadata-Version: 2.1
Name: logsparsersubsystem
Version: 1.0.6
Summary: logs parsing subsystem library for airflow
Author: DieNice
Author-email: DailyPlanning@bk.ru
Requires-Python: >=3.10,<4.0
Classifier: Programming Language :: Python :: 3
Classifier: Programming Language :: Python :: 3.10
Classifier: Programming Language :: Python :: 3.11
Requires-Dist: click (>=8.1.4,<9.0.0)
Requires-Dist: ip2location (>=8.10.0,<9.0.0)
Requires-Dist: matplotlib (>=3.7.2,<4.0.0)
Requires-Dist: pandas (>=2.0.3,<3.0.0)
Requires-Dist: pillow (>=10.0.0,<11.0.0)
Requires-Dist: requests (>=2.31.0,<3.0.0)
Requires-Dist: tqdm (>=4.65.0,<5.0.0)
